confighammer/ini.py
confighammer/yml.py
confighammer-0.0.1.dist-info/METADATA
confighammer-0.0.1.dist-info/WHEEL
confighammer-0.0.1.dist-info/top_level.txt
confighammer-0.0.1.dist-info/RECORD
