Metadata-Version: 2.1
Name: confighammer
Version: 0.0.1
Summary: Common Config Reader
Home-page: https://github.com/friendlyblackwell/confighammer
Author: Blackwell
Author-email: friendlyblackwell@example.com
Requires-Dist: PyYAML
